oceans/RPSstuff.py
oceans/__init__.py
oceans/_version.py
oceans/colormaps.py
oceans/datasets.py
oceans/filters.py
oceans/ocfis.py
oceans/plotting.py
oceans/synop.py
oceans/utilities.py
oceans/cmap_data/cbathy.dat
oceans/cmap_data/coolavhrrmap.dat
oceans/cmap_data/ctopo.dat
oceans/cmap_data/odv.dat
oceans/cmap_data/redblue_dark.dat
oceans/cmap_data/redblue_light.dat
oceans/cmap_data/redgreen.dat
oceans/cmap_data/rscolmap.dat
oceans/sandbox/lines.py
oceans/sandbox/data/testdata.npz
oceans/sw_extras/__init__.py
oceans/sw_extras/gamma_GP_from_SP_pt.py
oceans/sw_extras/sw_extras.py
oceans/sw_extras/waves.py
oceans-1.1.4.dist-info/LICENSE.txt
oceans-1.1.4.dist-info/METADATA
oceans-1.1.4.dist-info/WHEEL
oceans-1.1.4.dist-info/top_level.txt
oceans-1.1.4.dist-info/RECORD
