Metadata-Version: 2.1
Name: oceans
Version: 1.1.4
Summary: Misc functions for oceanographic data analysis
Maintainer: André Palóczy, Arnaldo Russo
Maintainer-email: Filipe Fernandes <ocefpaf+oceans@gmail.com>
License: Copyright (c) 2016, Filipe Fernandes
Project-URL: documentation, https://pyoceans.github.io/python-oceans/
Project-URL: homepage, https://pypi.python.org/pypi/oceans/
Project-URL: repository, https://github.com/pyoceans/python-oceans
Classifier: Programming Language :: Python :: 3 :: Only
Classifier: Programming Language :: Python :: 3.10
Classifier: Programming Language :: Python :: 3.11
Classifier: Programming Language :: Python :: 3.12
Requires-Python: >=3.10
License-File: LICENSE.txt
Requires-Dist: cmcrameri
Requires-Dist: contourpy
Requires-Dist: gsw
Requires-Dist: matplotlib >=3.6.0
Requires-Dist: numpy >=1.20
Requires-Dist: pandas >=1.0.1
Requires-Dist: seawater
Provides-Extra: extras
Requires-Dist: cartopy ; extra == 'extras'
Requires-Dist: iris ; extra == 'extras'
Requires-Dist: netcdf4 ; extra == 'extras'
Requires-Dist: pandas ; extra == 'extras'
Requires-Dist: scipy ; extra == 'extras'
